mcshapley/__init__.py
mcshapley/shaps.py
mcshapley/temporalUtils.py
mcshapley-0.0.2.dist-info/METADATA
mcshapley-0.0.2.dist-info/WHEEL
mcshapley-0.0.2.dist-info/licenses/LICENSE
mcshapley-0.0.2.dist-info/RECORD
