Metadata-Version: 2.3
Name: mcshapley
Version: 0.0.2
Summary: A package that is used to run Shapley value variations useful for research on CSV file. The package includes MC-Net Shapley which runs in polynomial time and Temporal Shapley which gives favor to coalition members on both performance and precedents. Both rely on certain assumptions, to learn more check the references.
Project-URL: Homepage, https://github.com/uwyo-mallet/Shapley-CVS--Gallegos-
Project-URL: Issues, https://github.com/uwyo-mallet/Shapley-CVS--Gallegos-/issues
Author-email: "Nikita A. Gallegos" <nikitaagallegos@gmail.com>
License-File: LICENSE
Classifier: Intended Audience :: Science/Research
Classifier: License :: OSI Approved :: MIT License
Classifier: Operating System :: OS Independent
Classifier: Programming Language :: Python :: 3
Requires-Python: >=3.10
Requires-Dist: numpy
Requires-Dist: scipy
Provides-Extra: tests
Requires-Dist: pytest; extra == 'tests'
